{
  "ticker": "PLTR",
  "period": "2024Q3",
  "form": "10-Q",
  "bs": {
    "total_assets": 4522425000,
    "stockholders_equity": 3475561000,
    "total_liabilities": 961460000
  },
  "pl": {
    "revenue": 1616662000,
    "net_income": 116434000,
    "eps_diluted": 0.05,
    "eps_basic": 0.05
  },
  "cf": {
    "operating_cash_flow": 411011000,
    "capital_expenditure": 10254000,
    "free_cash_flow": 400757000
  },
  "shares": {
    "shares_diluted": 2281347000,
    "shares_basic": 2134045000
  }
}