{
  "ticker": "SOUN",
  "period": "2023Q3",
  "form": "10-Q",
  "bs": {
    "total_assets": 144010000,
    "stockholders_equity": 25932000,
    "total_liabilities": 118078000
  },
  "pl": {
    "revenue": 28726000,
    "net_income": -70934000,
    "eps_diluted": -0.33,
    "eps_basic": -0.33
  },
  "cf": {
    "operating_cash_flow": -54395000,
    "capital_expenditure": 334000,
    "free_cash_flow": -54729000
  },
  "shares": {
    "shares_diluted": 222760880,
    "shares_basic": 222760880
  },
  "other": {
    "rpo": 13900000
  }
}